git_tools.py
prompt_helpers.py
server.py
iflow_mcp_aj_geddes_fastfs_mcp-2.8.0.dist-info/licenses/LICENSE
iflow_mcp_aj_geddes_fastfs_mcp-2.8.0.dist-info/METADATA
iflow_mcp_aj_geddes_fastfs_mcp-2.8.0.dist-info/WHEEL
iflow_mcp_aj_geddes_fastfs_mcp-2.8.0.dist-info/entry_points.txt
iflow_mcp_aj_geddes_fastfs_mcp-2.8.0.dist-info/top_level.txt
iflow_mcp_aj_geddes_fastfs_mcp-2.8.0.dist-info/RECORD
