Metadata-Version: 2.4
Name: iflow-mcp_aj-geddes_fastfs-mcp
Version: 2.8.0
Summary: A high-speed MCP (Model Context Protocol) server for filesystem operations, Git integration, and interactive prompting capabilities
Author-email: aj-geddes <aj-geddes@example.com>
License: MIT
Project-URL: Homepage, https://github.com/aj-geddes/fastfs-mcp
Project-URL: Repository, https://github.com/aj-geddes/fastfs-mcp
Project-URL: Issues, https://github.com/aj-geddes/fastfs-mcp/issues
Keywords: mcp,model-context-protocol,filesystem,git,fastmcp
Classifier: Development Status :: 4 - Beta
Classifier: Intended Audience :: Developers
Classifier: License :: OSI Approved :: MIT License
Classifier: Programming Language :: Python :: 3
Classifier: Programming Language :: Python :: 3.8
Classifier: Programming Language :: Python :: 3.9
Classifier: Programming Language :: Python :: 3.10
Classifier: Programming Language :: Python :: 3.11
Classifier: Programming Language :: Python :: 3.12
Classifier: Topic :: Software Development :: Libraries :: Python Modules
Requires-Python: >=3.8
License-File: LICENSE
Requires-Dist: fastmcp>=2.8.0
Requires-Dist: PyJWT>=2.8.0
Requires-Dist: cryptography>=41.0.4
Dynamic: license-file
